mytutor/__init__.py
mytutor-1.0.2.dist-info/LICENSE
mytutor-1.0.2.dist-info/METADATA
mytutor-1.0.2.dist-info/WHEEL
mytutor-1.0.2.dist-info/top_level.txt
mytutor-1.0.2.dist-info/RECORD
