Metadata-Version: 2.1
Name: mytutor
Version: 1.0.2
Summary: Jupyter notebook magic cell wrapper for online python tutor.
Home-page: https://github.com/ccha23/mytutor
Author: Chung Chan
License: MIT
Platform: UNKNOWN
Classifier: Framework :: IPython
Classifier: Programming Language :: Python
Classifier: License :: OSI Approved :: MIT License
License-File: LICENSE
